examples/__init__.py
examples/utils.py
mle_nl2query-1.1.34.dist-info/licenses/LICENSE
nl2query/__init__.py
nl2query/settings.py
nl2query/agent/__init__.py
nl2query/agent/graph.py
nl2query/agent/node_selector.py
nl2query/agent/nodes.py
nl2query/agent/state.py
nl2query/connectors/__init__.py
nl2query/core/__init__.py
nl2query/core/base_module.py
nl2query/core/decorators.py
nl2query/core/exceptions.py
nl2query/core/llm_models.py
nl2query/core/logger.py
nl2query/core/path_setup.py
nl2query/core/utils/__init__.py
nl2query/core/utils/helper.py
nl2query/db/__init__.py
nl2query/db/db_connector.py
nl2query/evaluation/__init__.py
nl2query/intent_ambiguity_handler/__init__.py
nl2query/intent_ambiguity_handler/main.py
nl2query/intent_engine/__init__.py
nl2query/intent_engine/main.py
nl2query/intent_engine/prompts.py
nl2query/intent_engine/schema.py
nl2query/query_builder/__init__.py
nl2query/query_builder/main.py
nl2query/query_builder/prompts.py
nl2query/query_builder/schema.py
nl2query/query_cacher/__init__.py
nl2query/query_cacher/main.py
nl2query/query_executor/__init__.py
nl2query/query_executor/main.py
nl2query/query_reframer/__init__.py
nl2query/query_reframer/main.py
nl2query/query_reframer/prompts.py
nl2query/query_reframer/schema.py
nl2query/query_validator/__init__.py
nl2query/query_validator/main.py
nl2query/query_validator/prompts.py
nl2query/query_validator/schema.py
nl2query/table_selector/__init__.py
nl2query/table_selector/main.py
nl2query/table_selector/prompts.py
nl2query/table_selector/schema.py
notebooks/__init__.py
scripts/__init__.py
scripts/fox_usecase.py
tests/__init__.py
mle_nl2query-1.1.34.dist-info/METADATA
mle_nl2query-1.1.34.dist-info/WHEEL
mle_nl2query-1.1.34.dist-info/top_level.txt
mle_nl2query-1.1.34.dist-info/RECORD
