Metadata-Version: 2.4
Name: mle-nl2query
Version: 1.1.34
Summary: nl2query package
Home-page: https://github.com/RamailoTech/mle_nl2query
Author: Palistha Deshar
Author-email: palisthadeshar@gmail.com
License: MIT
Classifier: Programming Language :: Python :: 3
Classifier: License :: OSI Approved :: MIT License
Classifier: Operating System :: OS Independent
Requires-Python: >=3.6
License-File: LICENSE
Requires-Dist: requests
Dynamic: author
Dynamic: author-email
Dynamic: classifier
Dynamic: description-content-type
Dynamic: home-page
Dynamic: license
Dynamic: license-file
Dynamic: requires-dist
Dynamic: requires-python
Dynamic: summary
